aidk_framework/__init__.py
aidk_framework/ai_dev_kit.py
aidk_framework/data.py
aidk_framework/deep_rnn.py
aidk_framework/deep_rnnFast.py
aidk_framework/default_network.py
aidk_framework/gan.py
aidk_framework/install.py
aidk_framework/network.py
aidk_framework/networkFast.py
aidk_framework/neuralnet_module.py
aidk_framework/neuromorphic_nn.py
aidk_framework/prediction_module.py
aidk_framework/probmax.py
aidk_framework/requirements.txt
aidk_framework/resnet.py
aidk_framework/resnetFast.py
aidk_framework/rfcn.py
aidk_framework/rfcnFast.py
aidk_framework/token_manager.py
aidk_framework/tranformers_module.py
aidk_framework/words.txt
aidk_framework-1.0.6.dist-info/METADATA
aidk_framework-1.0.6.dist-info/WHEEL
aidk_framework-1.0.6.dist-info/top_level.txt
aidk_framework-1.0.6.dist-info/RECORD
