Metadata-Version: 2.4
Name: aidk_framework
Version: 1.0.6
Summary: Artificial Intelligence Development Kit (AIDK) – unified, production-grade AI framework
Author: Akshansh Nandan
Author-email: Akshansh Nandan <microcodehack@gmail.com>
License: GNU General Public License
Project-URL: Homepage, https://github.com/Akshansh-Nandan/Tech/tree/AI/AI_lib
Project-URL: Documentation, https://github.com/Akshansh-Nandan/Tech/tree/AI/AI_lib
Project-URL: Source, https://github.com/Akshansh-Nandan/Tech/tree/AI/AI_lib
Keywords: artificial-intelligence,machine-learning,deep-learning,neural-networks,transformers,meta-learning
Classifier: Development Status :: 5 - Production/Stable
Classifier: Intended Audience :: Developers
Classifier: Topic :: Scientific/Engineering :: Artificial Intelligence
Classifier: Programming Language :: Python :: 3
Classifier: Programming Language :: Python :: 3.10
Classifier: Operating System :: POSIX :: Linux
Classifier: License :: Other/Proprietary License
Requires-Python: ==3.10.*
